EasyFileHandling/__init__.py
EasyFileHandling/imagehandler.py
EasyFileHandling/jsonHandler.py
EasyFileHandling/main.py
EasyFileHandling/beta/__init__.py
EasyFileHandling/beta/main.py
EasyFileHandling/errors/__init__.py
EasyFileHandling/errors/error.py
EasyFileHandling/tests/__init__.py
EasyFileHandling/tests/test_filehandler.py
EasyFileHandling-1.5.2.dist-info/LICENSE
EasyFileHandling-1.5.2.dist-info/METADATA
EasyFileHandling-1.5.2.dist-info/WHEEL
EasyFileHandling-1.5.2.dist-info/top_level.txt
EasyFileHandling-1.5.2.dist-info/RECORD
