Metadata-Version: 2.1
Name: EasyFileHandling
Version: 1.5.2
Summary: A simple and useful package for File Handling
Home-page: https://github.com/ProjectsWithPython/FileHandling
Author: Haider Ali
Author-email: 
License: UNKNOWN
Project-URL: Bug Tracker, https://github.com/ProjectsWithPython/FileHandling/issues
Platform: UNKNOWN
Classifier: Programming Language :: Python :: 3
Classifier: License :: OSI Approved :: MIT License
Classifier: Operating System :: OS Independent
Requires-Python: >=3.6
License-File: LICENSE
Requires-Dist: Pillow
